Img_Processing_py/__init__.py
Img_Processing_py/processing/__init__.py
Img_Processing_py/processing/combination.py
Img_Processing_py/processing/transformation.py
Img_Processing_py/utils/__init__.py
Img_Processing_py/utils/io.py
Img_Processing_py/utils/plot.py
Img_Processing_py-0.0.4.dist-info/METADATA
Img_Processing_py-0.0.4.dist-info/WHEEL
Img_Processing_py-0.0.4.dist-info/top_level.txt
Img_Processing_py-0.0.4.dist-info/RECORD
