Metadata-Version: 2.1
Name: Img-Processing-py
Version: 0.0.4
Summary: Image Processing Package using Skimage
Home-page: https://github.com/VagnerF/Pacotes_processamento_imagens_com_python
Author: VagnerF
Requires-Python: >=3.7
Requires-Dist: matplotlib
Requires-Dist: numpy
Requires-Dist: scikit-image (>=0.16.1)
